__init__.py
agent/__init__.py
agent/constants.py
agent/ttypes.py
ai/__init__.py
ai/chronon/__init__.py
ai/chronon/airflow_helpers.py
ai/chronon/click_helpers.py
ai/chronon/constants.py
ai/chronon/data_types.py
ai/chronon/group_by.py
ai/chronon/join.py
ai/chronon/logger.py
ai/chronon/model.py
ai/chronon/query.py
ai/chronon/query_utils.py
ai/chronon/schedule_validation.py
ai/chronon/source.py
ai/chronon/staging_query.py
ai/chronon/types.py
ai/chronon/utils.py
ai/chronon/windows.py
ai/chronon/cli/__init__.py
ai/chronon/cli/formatter.py
ai/chronon/cli/git_utils.py
ai/chronon/cli/logger.py
ai/chronon/cli/compile/__init__.py
ai/chronon/cli/compile/column_hashing.py
ai/chronon/cli/compile/compile_context.py
ai/chronon/cli/compile/compiler.py
ai/chronon/cli/compile/conf_validator.py
ai/chronon/cli/compile/fill_templates.py
ai/chronon/cli/compile/parse_configs.py
ai/chronon/cli/compile/parse_teams.py
ai/chronon/cli/compile/serializer.py
ai/chronon/cli/compile/version_utils.py
ai/chronon/cli/compile/display/__init__.py
ai/chronon/cli/compile/display/class_tracker.py
ai/chronon/cli/compile/display/compile_status.py
ai/chronon/cli/compile/display/compiled_obj.py
ai/chronon/cli/compile/display/console.py
ai/chronon/cli/compile/display/diff_result.py
ai/chronon/repo/__init__.py
ai/chronon/repo/aws.py
ai/chronon/repo/cluster.py
ai/chronon/repo/compile.py
ai/chronon/repo/constants.py
ai/chronon/repo/default_runner.py
ai/chronon/repo/explore.py
ai/chronon/repo/extract_objects.py
ai/chronon/repo/gcp.py
ai/chronon/repo/gitpython_utils.py
ai/chronon/repo/hub_runner.py
ai/chronon/repo/hub_uploader.py
ai/chronon/repo/init.py
ai/chronon/repo/join_backfill.py
ai/chronon/repo/run.py
ai/chronon/repo/serializer.py
ai/chronon/repo/team_json_utils.py
ai/chronon/repo/utils.py
ai/chronon/repo/zipline.py
ai/chronon/repo/zipline_hub.py
ai/chronon/resources/__init__.py
ai/chronon/resources/gcp/__init__.py
ai/chronon/resources/gcp/teams.py
ai/chronon/resources/gcp/group_bys/__init__.py
awx_zipline_ai-0.4.3.dist-info/METADATA
awx_zipline_ai-0.4.3.dist-info/WHEEL
awx_zipline_ai-0.4.3.dist-info/entry_points.txt
awx_zipline_ai-0.4.3.dist-info/top_level.txt
awx_zipline_ai-0.4.3.dist-info/RECORD
